pypi_project_no_license/__init__.py
pypi_project_no_meta/__init__.py
pypi_project_no_meta-0.1.0.dist-info/METADATA
pypi_project_no_meta-0.1.0.dist-info/WHEEL
pypi_project_no_meta-0.1.0.dist-info/top_level.txt
pypi_project_no_meta-0.1.0.dist-info/RECORD
