Metadata-Version: 2.1
Name: pypi-project-no-meta
Version: 0.1.0
Summary: PyPI minimal project with no meta
Author: pilosus
